nonebot_plugin_chatrecorder/__init__.py
nonebot_plugin_chatrecorder/adapters/__init__.py
nonebot_plugin_chatrecorder/adapters/console.py
nonebot_plugin_chatrecorder/adapters/discord.py
nonebot_plugin_chatrecorder/adapters/dodo.py
nonebot_plugin_chatrecorder/adapters/feishu.py
nonebot_plugin_chatrecorder/adapters/kaiheila.py
nonebot_plugin_chatrecorder/adapters/onebot_v11.py
nonebot_plugin_chatrecorder/adapters/onebot_v12.py
nonebot_plugin_chatrecorder/adapters/qq.py
nonebot_plugin_chatrecorder/adapters/satori.py
nonebot_plugin_chatrecorder/adapters/telegram.py
nonebot_plugin_chatrecorder/config.py
nonebot_plugin_chatrecorder/consts.py
nonebot_plugin_chatrecorder/exception.py
nonebot_plugin_chatrecorder/message.py
nonebot_plugin_chatrecorder/migrations/bc43ce947963_data_migrate.py
nonebot_plugin_chatrecorder/migrations/ea78280f71da_init_db.py
nonebot_plugin_chatrecorder/model.py
nonebot_plugin_chatrecorder/record.py
nonebot_plugin_chatrecorder/record.pyi
nonebot_plugin_chatrecorder/utils.py
nonebot_plugin_chatrecorder-0.7.0.dist-info/LICENSE
nonebot_plugin_chatrecorder-0.7.0.dist-info/METADATA
nonebot_plugin_chatrecorder-0.7.0.dist-info/WHEEL
nonebot_plugin_chatrecorder-0.7.0.dist-info/RECORD
