Metadata-Version: 2.1
Name: nonebot_plugin_chatrecorder
Version: 0.7.0
Summary: 适用于 Nonebot2 的聊天记录插件
Home-page: https://github.com/noneplugin/nonebot-plugin-chatrecorder
License: MIT
Author: meetwq
Author-email: meetwq@gmail.com
Requires-Python: >=3.9,<4.0
Classifier: License :: OSI Approved :: MIT License
Classifier: Programming Language :: Python :: 3
Classifier: Programming Language :: Python :: 3.9
Classifier: Programming Language :: Python :: 3.10
Classifier: Programming Language :: Python :: 3.11
Classifier: Programming Language :: Python :: 3.12
Classifier: Programming Language :: Python :: 3.13
Requires-Dist: nonebot-plugin-localstore (>=0.6.0,<1.0.0)
Requires-Dist: nonebot-plugin-orm (>=0.7.0,<1.0.0)
Requires-Dist: nonebot-plugin-uninfo (>=0.6.1,<1.0.0)
Requires-Dist: nonebot2 (>=2.3.0,<3.0.0)
Project-URL: Repository, https://github.com/noneplugin/nonebot-plugin-chatrecorder
